mkpipe_loader_oracledb/__init__.py
mkpipe_loader_oracledb/jars/com.oracle.database.jdbc_ojdbc11-23.6.0.24.10.jar
mkpipe_loader_oracledb-0.1.0.dist-info/LICENSE
mkpipe_loader_oracledb-0.1.0.dist-info/METADATA
mkpipe_loader_oracledb-0.1.0.dist-info/WHEEL
mkpipe_loader_oracledb-0.1.0.dist-info/entry_points.txt
mkpipe_loader_oracledb-0.1.0.dist-info/top_level.txt
mkpipe_loader_oracledb-0.1.0.dist-info/RECORD
